intent_cli/__init__.py
intent_cli/__main__.py
intent_cli/verify.py
intentlayer_sdk/__init__.py
intentlayer_sdk/client.py
intentlayer_sdk/config.py
intentlayer_sdk/envelope.py
intentlayer_sdk/exceptions.py
intentlayer_sdk/models.py
intentlayer_sdk/networks.json
intentlayer_sdk/py.typed
intentlayer_sdk/signer/__init__.py
intentlayer_sdk/signer/local.py
intentlayer_sdk/utils.py
intentlayer_sdk/version.py
intentlayer_sdk-0.3.0.dist-info/LICENSE
intentlayer_sdk-0.3.0.dist-info/METADATA
intentlayer_sdk-0.3.0.dist-info/WHEEL
intentlayer_sdk-0.3.0.dist-info/entry_points.txt
intentlayer_sdk-0.3.0.dist-info/RECORD
