Metadata-Version: 2.3
Name: intentlayer-sdk
Version: 0.3.0
Summary: Python SDK for IntentLayer - handles intent recording and IPFS pinning
License: MIT License
Author: Ryan Sevey
Author-email: dev@intentlayer.net
Requires-Python: >=3.11,<4.0
Classifier: License :: OSI Approved :: MIT License
Classifier: Programming Language :: Python :: 3
Classifier: Programming Language :: Python :: 3.11
Requires-Dist: base58 (>=2.1.1)
Requires-Dist: cryptography (>=44.0.0)
Requires-Dist: pydantic (>=2.5.0)
Requires-Dist: requests (>=2.31.0)
Requires-Dist: typer (>=0.9.0)
Requires-Dist: web3 (>=7.10.0,<8.0.0)
